strym/DBC_Read_Tools.py
strym/README.md
strym/TODO.todo
strym/__init__.py
strym/config.py
strym/meta.py
strym/strym.py
strym/strymmap.py
strym/strymread.py
strym/tools.py
strym/version
strym/dbc/honda_pilot_2017.dbc
strym/dbc/nissan_rogue_2021.dbc
strym/dbc/nissan_rogue_experimental.dbc
strym/dbc/toyota_rav4_2019.dbc
strym/dbc/toyota_rav4_2020.dbc
strym/dbc/toyota_rav4_2021.dbc
strym/dbc/toyota_rav4_hybrid.dbc
strym/utils/__init__.py
strym/utils/log.py
strym/vin_parser/__init__.py
strym/vin_parser/core.py
strym/vin_parser/nhtsa.py
strym_stripped-0.5.1.dist-info/LICENSE
strym_stripped-0.5.1.dist-info/METADATA
strym_stripped-0.5.1.dist-info/WHEEL
strym_stripped-0.5.1.dist-info/top_level.txt
strym_stripped-0.5.1.dist-info/RECORD
