Metadata-Version: 2.1
Name: strym-stripped
Version: 0.5.1
Summary: A real time CAN data analysis tool.
Home-page: https://github.com/jmscslgroup/strym
Author: Alex Richardson
Author-email: william.a.richardson@vanderbilt.edu
Keywords: candata,can,autonomous vehicle,ACC,adaptive cruise control,Panda,Traffic,Transportation,visualization
Classifier: Programming Language :: Python :: 3
Classifier: Framework :: AsyncIO
Classifier: Topic :: Communications
Classifier: Topic :: Scientific/Engineering :: Visualization
Classifier: License :: OSI Approved :: MIT License
Requires-Python: >3.12
License-File: LICENSE
Requires-Dist: pandas
Requires-Dist: setuptools
Requires-Dist: setuptools-scm
Requires-Dist: importlib-resources
Requires-Dist: importlib-metadata
Requires-Dist: numpy
Requires-Dist: cantools >=39.4.5
Requires-Dist: ipython
Requires-Dist: scipy >=1.14.0
Requires-Dist: python-dotenv
Requires-Dist: packaging
Requires-Dist: requests
